synapses_py/__init__.py
synapses_py/library.py
synapses_py/model/draw.py
synapses_py/model/encoding/continuous_attribute.py
synapses_py/model/encoding/discrete_attribute.py
synapses_py/model/encoding/preprocessor.py
synapses_py/model/encoding/serialization.py
synapses_py/model/mathematics.py
synapses_py/model/net_elems/activation.py
synapses_py/model/net_elems/layer.py
synapses_py/model/net_elems/network.py
synapses_py/model/net_elems/neuron.py
synapses_py/model/utilities.py
synapses_py-7.4.1.dist-info/WHEEL
synapses_py-7.4.1.dist-info/METADATA
synapses_py-7.4.1.dist-info/RECORD
