Metadata-Version: 2.1
Name: synapses-py
Version: 7.4.1
Summary: A lightweight library for neural networks that runs anywhere
Home-page: https://mrdimosthenis.github.io/Synapses
License: MIT
Keywords: neural-network,machine-learning,deep-learning,functional-programming
Author: Dimosthenis Michailidis
Author-email: mrdimosthenis@hotmail.com
Requires-Python: >=3.6.1,<4.0
Classifier: License :: OSI Approved :: MIT License
Classifier: Programming Language :: Python :: 3
Classifier: Programming Language :: Python :: 3.7
Classifier: Programming Language :: Python :: 3.8
Classifier: Programming Language :: Python :: 3.9
Requires-Dist: PyFunctional (>=1.4.3,<2.0.0)
Project-URL: Repository, https://github.com/mrdimosthenis/Synapses
